socketmapsql.py
socketmap_sql-0.2.0.dist-info/entry_points.txt
socketmap_sql-0.2.0.dist-info/LICENSE
socketmap_sql-0.2.0.dist-info/WHEEL
socketmap_sql-0.2.0.dist-info/METADATA
socketmap_sql-0.2.0.dist-info/RECORD
