Metadata-Version: 2.1
Name: socketmap-sql
Version: 0.2.0
Summary: An implementation of the sendmail socketmap protocol to allow an SQL database
Author-email: Keith Gaughan <k@stereochro.me>
Requires-Python: >=3.8
Classifier: Development Status :: 4 - Beta
Classifier: Intended Audience :: System Administrators
Classifier: License :: OSI Approved :: MIT License
Classifier: Operating System :: POSIX
Classifier: Programming Language :: Python :: 3
Classifier: Programming Language :: Python :: 3 :: Only
Classifier: Topic :: Communications :: Email :: Mail Transport Agents
Classifier: Topic :: Database
Project-URL: Source, https://github.com/kgaughan/socketmap-sql
